headscale_api/__init__.py
headscale_api/config.py
headscale_api/endpoints.py
headscale_api/headscale.py
headscale_api/py.typed
headscale_api/schema/__init__.py
headscale_api/schema/config.py
headscale_api/schema/google/__init__.py
headscale_api/schema/google/api/__init__.py
headscale_api/schema/headscale/__init__.py
headscale_api/schema/headscale/v1/__init__.py
headscale_api-0.2.0.dist-info/LICENSE
headscale_api-0.2.0.dist-info/METADATA
headscale_api-0.2.0.dist-info/WHEEL
headscale_api-0.2.0.dist-info/RECORD
