Metadata-Version: 2.1
Name: headscale-api
Version: 0.2.0
Summary: Python Headscale API and configuration abstraction.
Home-page: https://github.com/MarekPikula/python-headscale-api
License: MIT
Author: Marek Pikuła
Author-email: marek@serenitycode.dev
Maintainer: Marek Pikuła
Maintainer-email: marek@serenitycode.dev
Requires-Python: >=3.11,<4.0
Classifier: Development Status :: 3 - Alpha
Classifier: Intended Audience :: Developers
Classifier: License :: OSI Approved :: MIT License
Classifier: Operating System :: OS Independent
Classifier: Programming Language :: Python :: 3
Classifier: Programming Language :: Python :: 3.11
Requires-Dist: betterproto[compiler] (==2.0.0b5)
Requires-Dist: pydantic (>=1.10.7,<2.0.0)
Requires-Dist: pydantic-yaml[ruamel] (>=0.11.2,<0.12.0)
Requires-Dist: requests (>=2.28.2,<3.0.0)
Project-URL: Repository, https://github.com/MarekPikula/python-headscale-api
